{"cameraMode":{"drawMode":0,"name":"Shaded","section":"Shading Mode"},"sceneLighting":false,"audioPlay":false,"sceneViewState":{"m_AlwaysRefresh":false,"showFog":true,"showSkybox":false,"showFlares":true,"showImageEffects":true,"showParticleSystems":true,"showVisualEffectGraphs":true,"m_FxEnabled":true},"in2DMode":false,"pivot":{"x":7.163066864013672,"y":1.5000554323196412,"z":6.320362567901611},"rotation":{"x":-0.22684666514396668,"y":0.05402807518839836,"z":-0.012603980489075184,"w":-0.9723514914512634},"size":7.08717155456543,"orthographic":false}